{"content": {"suites": {"0": {"status": {"total_pass": 10, "total_skip": 1, "total_xpass": 0, "total_xfail": 0, "total_rerun": 0, "total_fail": 1, "total_error": 0}, "tests": {"0": {"status": "PASS", "message": "", "test_name": "test_lm_regression_suite[Advtracking]", "rerun": "0"}, "1": {"status": "PASS", "message": "", "test_name": "test_lm_regression_suite[Kynection]", "rerun": "0"}, "2": {"status": "PASS", "message": "", "test_name": "test_lm_regression_suite[Sensium]", "rerun": "0"}, "3": {"status": "PASS", "message": "", "test_name": "test_lm_regression_suite[Simplyunified]", "rerun": "0"}, "4": {"status": "SKIP", "message": "('/home/user/Downloads/LM_Regression/pageObjects/FleetPortalPage.py', 1285, 'Skipped: ************ User page not displayed **********')\n", "test_name": "test_lm_regression_suite[Tcvsat]", "rerun": "0"}, "5": {"status": "PASS", "message": "", "test_name": "test_lm_regression_suite[Intellitrac]", "rerun": "0"}, "6": {"status": "PASS", "message": "", "test_name": "test_lm_regression_suite[Magtec]", "rerun": "0"}, "7": {"status": "PASS", "message": "", "test_name": "test_lm_regression_suite[Easitrack]", "rerun": "0"}, "8": {"status": "PASS", "message": "", "test_name": "test_lm_regression_suite[Iotab]", "rerun": "0"}, "9": {"status": "PASS", "message": "", "test_name": "test_lm_regression_suite[Blackboxcontrol]", "rerun": "0"}, "10": {"status": "PASS", "message": "", "test_name": "test_lm_regression_suite[Spireonstage]", "rerun": "0"}, "11": {"status": "FAIL", "message": "   selenium.common.exceptions.NoSuchElementException: Message: no such element: Unable to locate element: {\"method\":\"xpath\",\"selector\":\"//button[@mattooltip='Launch fleet dashboard']\"}\n     (Session info: chrome=122.0.6261.111); For documentation on this error, please visit: https://www.selenium.dev/documentation/webdriver/troubleshooting/errors#no-such-element-exception\n   Stacktrace:\n   #0 0x5e76a4f98f33 <unknown>\n   #1 0x5e76a4c90ce6 <unknown>\n   #2 0x5e76a4cdbe48 <unknown>\n   #3 0x5e76a4cdbf01 <unknown>\n   #4 0x5e76a4d1f3f4 <unknown>\n   #5 0x5e76a4cfdedd <unknown>\n   #6 0x5e76a4d1c899 <unknown>\n   #7 0x5e76a4cfdc53 <unknown>\n   #8 0x5e76a4ccedb3 <unknown>\n   #9 0x5e76a4ccf77e <unknown>\n   #10 0x5e76a4f5e86b <unknown>\n   #11 0x5e76a4f62885 <unknown>\n   #12 0x5e76a4f4c181 <unknown>\n   #13 0x5e76a4f63412 <unknown>\n   #14 0x5e76a4f3025f <unknown>\n   #15 0x5e76a4f87528 <unknown>\n   #16 0x5e76a4f87723 <unknown>\n   #17 0x5e76a4f980e4 <unknown>\n   #18 0x7e1547a94ac3 <unknown>\n", "test_name": "test_lm_regression_suite[Geotab]", "rerun": "0"}}, "suite_name": "test_LM_RegressionSuite.py"}}}, "date": "April 21, 2025", "start_time": 1745233514.5069792, "total_suite": 1, "status": "FAIL", "status_list": {"pass": "10", "fail": "1", "skip": "1", "error": "0", "xpass": "0", "xfail": "0", "rerun": "0"}, "total_tests": "12"}